iso8583sim/__init__.py
iso8583sim/demo.py
iso8583sim/cli/__init__.py
iso8583sim/cli/commands.py
iso8583sim/cli/config.py
iso8583sim/cli/formatter.py
iso8583sim/cli/utils.py
iso8583sim/core/__init__.py
iso8583sim/core/_bitmap.pyx
iso8583sim/core/_parser_fast.pyx
iso8583sim/core/_validator_fast.pyx
iso8583sim/core/builder.py
iso8583sim/core/emv.py
iso8583sim/core/parser.py
iso8583sim/core/pool.py
iso8583sim/core/types.py
iso8583sim/core/validator.py
iso8583sim/llm/__init__.py
iso8583sim/llm/base.py
iso8583sim/llm/explainer.py
iso8583sim/llm/generator.py
iso8583sim/llm/prompts.py
iso8583sim/llm/providers/__init__.py
iso8583sim/llm/providers/anthropic.py
iso8583sim/llm/providers/google.py
iso8583sim/llm/providers/ollama.py
iso8583sim/llm/providers/openai.py
iso8583sim/utils/helpers.py
iso8583sim/web/app.py
iso8583sim-1.1.3.dist-info/METADATA
iso8583sim-1.1.3.dist-info/WHEEL
iso8583sim-1.1.3.dist-info/licenses/LICENSE
iso8583sim-1.1.3.dist-info/RECORD
