Metadata-Version: 2.4
Name: iso8583sim
Version: 1.1.3
Summary: High-performance ISO 8583 message simulator with CLI, Python SDK, and LLM features
Author-email: Subhadip Mitra <contact@subhadipmitra.com>
License: MIT License
License-File: LICENSE
Keywords: banking,financial,iso8583,payment,simulator
Classifier: Development Status :: 5 - Production/Stable
Classifier: Intended Audience :: Financial and Insurance Industry
Classifier: License :: OSI Approved :: MIT License
Classifier: Programming Language :: Python :: 3
Classifier: Programming Language :: Python :: 3.10
Classifier: Programming Language :: Python :: 3.11
Classifier: Programming Language :: Python :: 3.12
Classifier: Topic :: Office/Business :: Financial
Classifier: Topic :: Software Development :: Testing
Requires-Python: >=3.10
Requires-Dist: click>=8.0.0
Requires-Dist: fastapi>=0.68.0
Requires-Dist: pydantic>=2.0.0
Requires-Dist: rich>=10.0.0
Requires-Dist: typer>=0.4.0
Requires-Dist: uvicorn>=0.15.0
Provides-Extra: anthropic
Requires-Dist: anthropic>=0.40.0; extra == 'anthropic'
Provides-Extra: dev
Requires-Dist: black>=22.0.0; extra == 'dev'
Requires-Dist: coverage>=7.4.0; extra == 'dev'
Requires-Dist: cython>=3.0.0; extra == 'dev'
Requires-Dist: isort>=5.0.0; extra == 'dev'
Requires-Dist: mypy>=0.900; extra == 'dev'
Requires-Dist: pre-commit>=3.5.0; extra == 'dev'
Requires-Dist: pytest-cov>=4.1.0; extra == 'dev'
Requires-Dist: pytest-html>=4.1.1; extra == 'dev'
Requires-Dist: pytest>=7.0.0; extra == 'dev'
Requires-Dist: pyyaml>=6.0.0; extra == 'dev'
Requires-Dist: ruff>=0.0.290; extra == 'dev'
Provides-Extra: docs
Requires-Dist: mkdocs-material>=9.5.0; extra == 'docs'
Requires-Dist: mkdocs>=1.6.0; extra == 'docs'
Requires-Dist: mkdocstrings[python]>=0.24.0; extra == 'docs'
Provides-Extra: google
Requires-Dist: google-generativeai>=0.8.0; extra == 'google'
Provides-Extra: llm
Requires-Dist: anthropic>=0.40.0; extra == 'llm'
Requires-Dist: google-generativeai>=0.8.0; extra == 'llm'
Requires-Dist: ollama>=0.4.0; extra == 'llm'
Requires-Dist: openai>=1.50.0; extra == 'llm'
Provides-Extra: ollama
Requires-Dist: ollama>=0.4.0; extra == 'ollama'
Provides-Extra: openai
Requires-Dist: openai>=1.50.0; extra == 'openai'
Provides-Extra: perf
Requires-Dist: cython>=3.0.0; extra == 'perf'
Provides-Extra: test
Requires-Dist: coverage>=7.4.0; extra == 'test'
Requires-Dist: pytest-cov>=4.1.0; extra == 'test'
Requires-Dist: pytest-html>=4.1.1; extra == 'test'
Requires-Dist: pytest>=7.0.0; extra == 'test'
Requires-Dist: pyyaml>=6.0.0; extra == 'test'
